lattica_fhe_core/__init__.py
lattica_fhe_core/cpp_sdk.cpython-313-x86_64-linux-gnu.so
lattica_fhe_core/libsodium.so
lattica_fhe_core/libsodium.so.26
lattica_fhe_core/libsodium.so.26.3.0
lattica_fhe_core-0.10.0.dist-info/METADATA
lattica_fhe_core-0.10.0.dist-info/WHEEL
lattica_fhe_core-0.10.0.dist-info/top_level.txt
lattica_fhe_core-0.10.0.dist-info/RECORD
lattica_fhe_core-0.10.0.dist-info/licenses/LICENSE.md
