Metadata-Version: 2.4
Name: lattica-fhe-core
Version: 0.10.0
Summary: Lattica FHE Core Python Bindings
Author-email: "LatticaAI Inc." <support@lattica.ai>
Requires-Python: >=3.11
License-File: LICENSE.md
Requires-Dist: numpy<3.0.0,>=2.0.1
Requires-Dist: torch==2.9.1
Requires-Dist: pybind11>=2.13.6
Dynamic: license-file
